etabs/__init__.py
etabs/tex_table.py
etabs/tex_table_cell.py
etabs-0.2.0.dist-info/LICENSE
etabs-0.2.0.dist-info/METADATA
etabs-0.2.0.dist-info/WHEEL
etabs-0.2.0.dist-info/top_level.txt
etabs-0.2.0.dist-info/RECORD
