Metadata-Version: 2.1
Name: etabs
Version: 0.2.0
Summary: Python library for rendering latex tables in an easy way
Author-email: Jorge Morgado Vega <jorge.morgadov@gmail.com>
License: MIT License
Project-URL: Homepage, https://github.com/jmorgadov/etabs
Keywords: latex,table
Classifier: License :: OSI Approved :: MIT License
Classifier: Programming Language :: Python
Classifier: Programming Language :: Python :: 3
Requires-Python: >=3.7
License-File: LICENSE
Provides-Extra: dev
Requires-Dist: black; extra == "dev"
Requires-Dist: pylint; extra == "dev"
Requires-Dist: bumpver; extra == "dev"
Requires-Dist: isort; extra == "dev"
Requires-Dist: pytest; extra == "dev"
